pixelfeeder/__init__.py
pixelfeeder/cli.py
pixelfeeder/export_cli.py
pixelfeeder/flickr_data_reader.py
pixelfeeder/gui.py
pixelfeeder/image_loader.py
pixelfeeder/metadata_types.py
pixelfeeder/pixelfed_client.py
pixelfeeder/tools.py
pixelfeeder-0.2.0.dist-info/LICENSE
pixelfeeder-0.2.0.dist-info/METADATA
pixelfeeder-0.2.0.dist-info/WHEEL
pixelfeeder-0.2.0.dist-info/entry_points.txt
pixelfeeder-0.2.0.dist-info/top_level.txt
pixelfeeder-0.2.0.dist-info/RECORD
