Metadata-Version: 2.1
Name: pixelfeeder
Version: 0.2.0
Summary: Import Flickr data into a Pixelfed account
Home-page: https://gitlab.com/bergentroll/pixelfeeder
Author: Anton Karmanov
Author-email: a.karmanov@inventati.org
License: Apache
Classifier: Environment :: X11 Applications
Classifier: License :: OSI Approved :: Apache Software License
Classifier: Operating System :: OS Independent
Classifier: Programming Language :: Python :: 3
Classifier: Topic :: Multimedia :: Graphics
Classifier: Topic :: Utilities
Requires-Python: >=3.8
License-File: LICENSE
Requires-Dist: Pillow <11,>=9.4
Requires-Dist: PyYAML ~=6.0
Requires-Dist: argcomplete ~=3.0
Requires-Dist: httpx ~=0.23
Requires-Dist: xdg ~=5.1
